.gitignore
README.txt
setup.cfg
setup.py
bopen/__init__.py
bopen.recipe.libinc.egg-info/PKG-INFO
bopen.recipe.libinc.egg-info/SOURCES.txt
bopen.recipe.libinc.egg-info/dependency_links.txt
bopen.recipe.libinc.egg-info/entry_points.txt
bopen.recipe.libinc.egg-info/namespace_packages.txt
bopen.recipe.libinc.egg-info/not-zip-safe
bopen.recipe.libinc.egg-info/requires.txt
bopen.recipe.libinc.egg-info/top_level.txt
bopen/recipe/__init__.py
bopen/recipe/libinc/README.txt
bopen/recipe/libinc/__init__.py
bopen/recipe/libinc/tests.py
bopen/recipe/libinc/testdata/sample-config