Metadata-Version: 1.0
Name: bopen.recipe.libinc
Version: 0.3.0
Summary: zc.buildout recipe that parses compile time options from config scripts
Home-page: http://www.bopen.eu/open-source/bopen.recipe.libinc
Author: Alessandro Amici
Author-email: a.amici@bopen.eu
License: ZPL
Keywords: development buildout recipe
Platform: UNKNOWN
Classifier: Framework :: Buildout
Classifier: Programming Language :: Python
Classifier: Intended Audience :: Developers
Classifier: Topic :: Software Development :: Build Tools
Classifier: Topic :: Software Development :: Libraries :: Python Modules
